jdata/__init__.py
jdata/__main__.py
jdata/csv.py
jdata/h5.py
jdata/jdata.py
jdata/jdict.py
jdata/jfile.py
jdata/jgifti.py
jdata/jnifti.py
jdata/jpath.py
jdata/jschema.py
jdata/neurojson.py
jdata/njprep.py
jdata-0.9.3.dist-info/licenses/LICENSE.txt
jdata-0.9.3.dist-info/METADATA
jdata-0.9.3.dist-info/WHEEL
jdata-0.9.3.dist-info/top_level.txt
jdata-0.9.3.dist-info/RECORD
